optibar/__init__.py
optibar-1.0.2.dist-info/METADATA
optibar-1.0.2.dist-info/WHEEL
optibar-1.0.2.dist-info/top_level.txt
optibar-1.0.2.dist-info/RECORD
