Metadata-Version: 2.1
Name: optibar
Version: 1.0.2
Summary: Make Advanced And Customizable ProgressBar
Author: VenzTechnolo
Author-email: venztechnolo@gmail.com
Keywords: python,progress,progressbar,fast,bar,python3
Classifier: Environment :: Console
Classifier: Intended Audience :: Developers
Classifier: Programming Language :: Python :: 3
Classifier: Development Status :: 4 - Beta
